milapy/__init__.py
milapy/_chain.py
milapy-0.1.0.dist-info/METADATA
milapy-0.1.0.dist-info/WHEEL
milapy-0.1.0.dist-info/RECORD
