Metadata-Version: 2.1
Name: milapy
Version: 0.1.0
Summary: 
Author: pyk
Author-email: gm@pyk.sh
Requires-Python: >=3.8
Classifier: Programming Language :: Python :: 3
Classifier: Programming Language :: Python :: 3.8
Classifier: Programming Language :: Python :: 3.9
Classifier: Programming Language :: Python :: 3.10
Classifier: Programming Language :: Python :: 3.11
Classifier: Programming Language :: Python :: 3.12
Requires-Dist: httpx (==0.25.2)
